[
  {
    "title": "Kono Massage-ya ga Sugoi! | 这家按摩店真厉害！",
    "code": "607904",
    "imageUrl": "https://via.placeholder.com/200x250.png?text=Image+Failed",
    "targetUrl": "https://nhentai.net/g/607904/",
    "tags": [
      "milf",
      "big breasts",
      "netorare",
      "cheating",
      "urination",
      "nakadashi",
      "ahegao",
      "huge breasts",
      "hairy",
      "translated",
      "dark skin",
      "x-ray",
      "big areolae",
      "impregnation",
      "blowjob",
      "chinese",
      "muscle",
      "big penis",
      "deepthroat",
      "doujinshi",
      "sole female",
      "original",
      "keoya",
      "keoya",
      "multiple orgasms",
      "painted nails"
    ],
    "category": "comic"
  },
  {
    "title": "影片: SSNI-123",
    "code": "SSNI-123",
    "imageUrl": "images/video_SSNI-123.jpg",
    "targetUrl": "https://missav.ws/dm28/ssni-123",
    "tags": [
      "video"
    ],
    "details": {},
    "category": "video"
  }
]