[
  {
    "title": "レイカは華麗な僕の女王 THE ANIMATION 第1巻 [中文字幕] - Hanime1.me",
    "imageUrl": "images/anime_115139.jpg",
    "targetUrl": "https://hanime1.me/watch?v=115139",
    "tags": [
      "anime"
    ],
    "category": "anime"
  },
  {
    "title": "Save 58.1",
    "code": "607463",
    "imageUrl": "https://via.placeholder.com/200x250.png?text=Image+Failed",
    "targetUrl": "https://nhentai.net/g/607463/",
    "tags": [
      "squirting",
      "big breasts",
      "nakadashi",
      "sex toys",
      "bondage",
      "translated",
      "x-ray",
      "lactation",
      "stockings",
      "chinese",
      "shotacon",
      "doujinshi",
      "sole female",
      "sole male",
      "kemonomimi",
      "original",
      "tail",
      "gloves",
      "signalred",
      "uragaeru"
    ],
    "category": "comic"
  },
  {
    "title": "Futari ga Shiawase ni Natteiku Sugata o Miru Kurai nara Shinda Hou ga Ii.  | 與其看著兩人幸福的樣子或許死會更輕鬆",
    "code": "547647",
    "imageUrl": "https://via.placeholder.com/200x250.png?text=Image+Failed",
    "targetUrl": "https://nhentai.net/g/547647/",
    "tags": [
      "virginity",
      "big breasts",
      "schoolboy uniform",
      "glasses",
      "netorare",
      "cheating",
      "schoolgirl uniform",
      "condom",
      "translated",
      "defloration",
      "tall girl",
      "chinese",
      "doujinshi",
      "sole male",
      "sakayama shinta",
      "umemoto seisaku iinkai",
      "beauty mark",
      "original",
      "eye-covering bang"
    ],
    "category": "comic"
  },
  {
    "title": "TS Panic Ch. 1-3",
    "code": "123456",
    "imageUrl": "images/123456.jpg",
    "targetUrl": "https://nhentai.net/g/123456/",
    "tags": [
      "big breasts",
      "cunnilingus",
      "mmf threesome",
      "schoolboy uniform",
      "group",
      "fujikawa satoshi",
      "english",
      "nakadashi",
      "anal",
      "demon girl",
      "translated",
      "lolicon",
      "hairjob",
      "defloration",
      "mind control",
      "possession",
      "gokkun",
      "bukkake",
      "rape",
      "blowjob",
      "gender bender",
      "manga"
    ],
    "category": "comic"
  },
  {
    "title": "Ai to Bouryoku to Skin- LOVE, VIOLENCE AND SKIN. | 爱与暴力与皮囊",
    "code": "582441",
    "imageUrl": "https://via.placeholder.com/200x250.png?text=Image+Failed",
    "targetUrl": "https://nhentai.net/g/582441/",
    "tags": [
      "futanari",
      "translated",
      "chinese dress",
      "blowjob",
      "chinese",
      "doujinshi",
      "sole female",
      "sole dickgirl",
      "orihi chihiro",
      "virophilia",
      "love live hasunosora jogakuin school idol club",
      "dickgirl on female",
      "ginko momose",
      "hime anyoji"
    ],
    "category": "comic"
  }
]